Metadata-Version: 1.0
Name: gagaussian
Version: 0.1
Summary: Probability distributions
Home-page: UNKNOWN
Author: UNKNOWN
Author-email: UNKNOWN
License: UNKNOWN
Platform: UNKNOWN
